breez_sdk/__init__.py
breez_sdk/breez_sdk.py
breez_sdk/libbreez_sdk_bindings.dylib
breez_sdk_lib-0.2.12.dist-info/METADATA
breez_sdk_lib-0.2.12.dist-info/WHEEL
breez_sdk_lib-0.2.12.dist-info/top_level.txt
breez_sdk_lib-0.2.12.dist-info/RECORD
