Metadata-Version: 2.1
Name: breez-sdk-lib
Version: 0.2.12
Summary: Python language bindings for the Breez SDK
Home-page: https://github.com/breez/breez-sdk
Author: Breez <contact@breez.technology>
License: MIT
Platform: UNKNOWN
